aoc/__init__.py
aoc/api_client.py
aoc/configuration.py
aoc/exceptions.py
aoc/image_utils.py
aoc/rest.py
aoc/utils.py
aoc/api/__init__.py
aoc/api/alert_api.py
aoc/api/cluster_api.py
aoc/api/content_library_image_api.py
aoc/api/content_library_vm_template_api.py
aoc/api/datacenter_api.py
aoc/api/deploy_api.py
aoc/api/elf_image_api.py
aoc/api/elf_storage_policy_api.py
aoc/api/everoute_cluster_api.py
aoc/api/everoute_license_api.py
aoc/api/everoute_package_api.py
aoc/api/gpu_device_api.py
aoc/api/host_api.py
aoc/api/iscsi_lun_api.py
aoc/api/iscsi_lun_snapshot_api.py
aoc/api/iscsi_target_api.py
aoc/api/isolation_policy_api.py
aoc/api/label_api.py
aoc/api/network_policy_rule_service_api.py
aoc/api/nic_api.py
aoc/api/observability_api.py
aoc/api/organization_api.py
aoc/api/ovf_api.py
aoc/api/security_group_api.py
aoc/api/security_policy_api.py
aoc/api/svt_image_api.py
aoc/api/system_audit_log_api.py
aoc/api/task_api.py
aoc/api/upload_task_api.py
aoc/api/usb_device_api.py
aoc/api/user_api.py
aoc/api/user_audit_log_api.py
aoc/api/user_role_next_api.py
aoc/api/v2_everoute_license_api.py
aoc/api/vds_api.py
aoc/api/virtual_private_cloud_api.py
aoc/api/virtual_private_cloud_cluster_binding_api.py
aoc/api/virtual_private_cloud_edge_gateway_api.py
aoc/api/virtual_private_cloud_edge_gateway_group_api.py
aoc/api/virtual_private_cloud_external_subnet_api.py
aoc/api/virtual_private_cloud_external_subnet_group_api.py
aoc/api/virtual_private_cloud_floating_ip_api.py
aoc/api/virtual_private_cloud_nat_gateway_api.py
aoc/api/virtual_private_cloud_route_table_api.py
aoc/api/virtual_private_cloud_router_gateway_api.py
aoc/api/virtual_private_cloud_security_group_api.py
aoc/api/virtual_private_cloud_security_policy_api.py
aoc/api/virtual_private_cloud_subnet_api.py
aoc/api/vlan_api.py
aoc/api/vm_api.py
aoc/api/vm_disk_api.py
aoc/api/vm_export_file_api.py
aoc/api/vm_folder_api.py
aoc/api/vm_nic_api.py
aoc/api/vm_placement_group_api.py
aoc/api/vm_snapshot_api.py
aoc/api/vm_template_api.py
aoc_sdk-1.0.0.dist-info/licenses/LICENSE
aoc_sdk-1.0.0.dist-info/METADATA
aoc_sdk-1.0.0.dist-info/WHEEL
aoc_sdk-1.0.0.dist-info/top_level.txt
aoc_sdk-1.0.0.dist-info/RECORD
