Metadata-Version: 2.4
Name: aoc-sdk
Version: 1.0.0
Summary: AOC APIs
Home-page: https://github.com/arcfraofficial/aoc-python-sdk
Author: AOC developers
Author-email: support@arcfra.com
Keywords: OpenAPI,OpenAPI-Generator,AOC APIs
License-File: LICENSE
Requires-Dist: urllib3>=1.25.3
Requires-Dist: six>=1.10
Requires-Dist: python-dateutil
Dynamic: author
Dynamic: author-email
Dynamic: description
Dynamic: description-content-type
Dynamic: home-page
Dynamic: keywords
Dynamic: license-file
Dynamic: requires-dist
Dynamic: summary
